hwpwings/__init__.py
hwpwings/custom.py
hwpwings/dataframe.py
hwpwings/etc_function.py
hwpwings/field.py
hwpwings/function_parts.py
hwpwings/keyboard.py
hwpwings/page.py
hwpwings/pictures.py
hwpwings/position.py
hwpwings/select.py
hwpwings/tablecell.py
hwpwings/text.py
hwpwings/use_hwp.py
hwpwings-0.4.7.dist-info/METADATA
hwpwings-0.4.7.dist-info/WHEEL
hwpwings-0.4.7.dist-info/top_level.txt
hwpwings-0.4.7.dist-info/RECORD
