Metadata-Version: 2.4
Name: hwpwings
Version: 0.4.7
Summary: 파이썬으로 한글 문서를 제어할 수 있는 두번째 라이브러리입니다.
Home-page: https://www.youtube.com/@한파엑셀
Author: 한파엑셀
Author-email: hpxl0518@gmail.com
Requires-Python: >=3.6
Requires-Dist: pywin32>=302
Requires-Dist: pandas>=1.0.0
Requires-Dist: lxml>=4.0.0
Dynamic: author
Dynamic: author-email
Dynamic: home-page
Dynamic: requires-dist
Dynamic: requires-python
Dynamic: summary
